elektro/__init__.py
elektro/api/__init__.py
elektro/api/project.json
elektro/api/schema.graphql
elektro/api/schema.py
elektro/arkitekt.py
elektro/builder.py
elektro/cli/__init__.py
elektro/cli/main.py
elektro/cli/schemas/v1.graphql
elektro/cli/utils.py
elektro/contrib/__init__.py
elektro/contrib/arkitekt/assignation_link.py
elektro/contrib/arkitekt/link.py
elektro/contrib/fakts/__init__.py
elektro/contrib/fakts/datalayer.py
elektro/datalayer.py
elektro/deployments/test/configs/mikro_next.yaml
elektro/deployments/test/configs/minio.yaml
elektro/deployments/test/docker-compose.yml
elektro/deployments/test/public_key.pem
elektro/elektro.py
elektro/errors.py
elektro/funcs.py
elektro/helpers.py
elektro/io/__init__.py
elektro/io/download.py
elektro/io/errors.py
elektro/io/types.py
elektro/io/upload.py
elektro/links/__init__.py
elektro/links/errors.py
elektro/links/upload.py
elektro/rath.py
elektro/rekuest.py
elektro/scalars.py
elektro/testing/__init__.py
elektro/testing/datalayer.py
elektro/traits.py
elektro/utils.py
elektro/vars.py
elektro/widgets.py
elektro-0.5.0.dist-info/METADATA
elektro-0.5.0.dist-info/WHEEL
elektro-0.5.0.dist-info/RECORD
