Metadata-Version: 2.1
Name: elektro
Version: 0.5.0
Summary: next images for arkitekt
License: CC BY-NC 3.0
Author: jhnnsrs
Author-email: jhnnsrs@gmail.com
Requires-Python: >=3.11,<4.0
Classifier: License :: Other/Proprietary License
Classifier: Programming Language :: Python :: 3
Classifier: Programming Language :: Python :: 3.11
Classifier: Programming Language :: Python :: 3.12
Provides-Extra: turms
Requires-Dist: dask (>=2024.12.1)
Requires-Dist: dokker (>=1.0.0)
Requires-Dist: numpy (>=1.26) ; python_version >= "3.12" and python_version < "4.0"
Requires-Dist: pandas (>=2.2)
Requires-Dist: rath (>=1.0.0)
Requires-Dist: s3fs (>=2024.10.0)
Requires-Dist: xarray (>=2024.11.0)
Requires-Dist: zarr (>3)
